gbm_autosplit/__init__.py
gbm_autosplit/auto_split_logic.py
gbm_autosplit/lgbm.py
gbm_autosplit/utils.py
gbm_autosplit/xgb.py
gbm_autosplit-0.0.12.dist-info/METADATA
gbm_autosplit-0.0.12.dist-info/WHEEL
gbm_autosplit-0.0.12.dist-info/top_level.txt
gbm_autosplit-0.0.12.dist-info/RECORD
