Metadata-Version: 2.1
Name: gbm-autosplit
Version: 0.0.12
Summary: LightGBM/XGBoost interface which tunes n_estimator by splitting data, then refit with entire data
Home-page: https://github.com/not-so-fat/gbm_autosplit
Author: @not-so-fat
Classifier: Programming Language :: Python :: 3
Classifier: License :: OSI Approved :: MIT License
Classifier: Operating System :: OS Independent
Requires-Python: >=3.6
Requires-Dist: lightgbm >=3.2.1
Requires-Dist: xgboost
Requires-Dist: pandas >=1.2.4
